edawishlist/MultiPandas2Plot.py
edawishlist/Pandas2Plot.py
edawishlist/__init__.py
edawishlist/axi_driver.py
edawishlist/axilite_simulation.py
edawishlist/ipbus2whishlist.py
edawishlist/memory.py
edawishlist/node.py
edawishlist/report.py
edawishlist/rtl_simulation.py
edawishlist/uhal_dummy_connection.py
edawishlist/utils.py
edawishlist/wishlist.py
edawishlist/wishlist_axi_node.py
edawishlist/wishlist_plotter.py
edawishlist/wishlist_robot.py
edawishlist-0.0.24.dist-info/METADATA
edawishlist-0.0.24.dist-info/WHEEL
edawishlist-0.0.24.dist-info/entry_points.txt
edawishlist-0.0.24.dist-info/licenses/LICENSE.md
edawishlist-0.0.24.dist-info/RECORD
